RobotFrameworkNetAddr/__init__.py
RobotFrameworkNetAddr/robotframeworknetaddr.py
robotframework_netaddr-0.0.4.dist-info/LICENSE
robotframework_netaddr-0.0.4.dist-info/METADATA
robotframework_netaddr-0.0.4.dist-info/WHEEL
robotframework_netaddr-0.0.4.dist-info/top_level.txt
robotframework_netaddr-0.0.4.dist-info/RECORD
